hiboutik/__init__.py
hiboutik/client.py
hiboutik/entity.py
hiboutik/entity_service.py
hiboutik/exception.py
hiboutik/service.py
tests/__init__.py
tests/test_client.py
tests/test_service.py
hiboutik-1.2.dist-info/LICENSE
hiboutik-1.2.dist-info/METADATA
hiboutik-1.2.dist-info/WHEEL
hiboutik-1.2.dist-info/top_level.txt
hiboutik-1.2.dist-info/RECORD
