Metadata-Version: 2.1
Name: hiboutik
Version: 1.2
Summary: Client library for Hiboutik APIs
Home-page: https://github.com/davaxi/python-hiboutik-api
Author: David Patiashvili
Author-email: stratagem.david+hiboutik@gmail.com
License: GPLv3+
License-File: LICENSE
